mad.py
madtornado4-4.3.0.data/scripts/mad.py
madtornado4-4.3.0.dist-info/LICENSE
madtornado4-4.3.0.dist-info/METADATA
madtornado4-4.3.0.dist-info/WHEEL
madtornado4-4.3.0.dist-info/entry_points.txt
madtornado4-4.3.0.dist-info/top_level.txt
madtornado4-4.3.0.dist-info/RECORD
