Metadata-Version: 2.1
Name: madtornado4
Version: 4.3.0
Summary: Madtornado is a tool for generating Tornado projects for MVC.【生成tornado MVC项目模板 CLI脚手架(scaffolding)】
Home-page: https://github.com/SystemLight/madtornado4
Author: SystemLight
Author-email: 1466335092@qq.com
Maintainer: SystemLight
Maintainer-email: 1466335092@qq.com
License: MIT
Download-URL: https://github.com/SystemLight/madtornado4/releases
Keywords: tornado,web,http_server,mt,Mad_tornado,madtornado,Tornado project template,python3,mvc,mad,generate the Tornado project,tornado cli,tornado mvc,tornado脚手架,生成tornado项目
Platform: Windows
Platform: Linux
Classifier: Development Status :: 3 - Alpha
Classifier: Intended Audience :: Developers
Classifier: Topic :: Software Development :: Build Tools
Classifier: License :: OSI Approved :: MIT License
Classifier: Programming Language :: Python :: 3.5
Classifier: Programming Language :: Python :: 3.6
Classifier: Programming Language :: Python :: 3.7
Classifier: Programming Language :: Python :: 3.8
Requires-Python: >=3.5
Requires-Dist: tornado (==6.1.0)
Requires-Dist: aiomysql (==0.0.20)
